pubq/__init__.py
pubq/app.py
pubq/auth.py
pubq/channel_manager.py
pubq/connection.py
pubq/connection_manager.py
pubq/defaults/__init__.py
pubq/defaults/default_channel_events.py
pubq/defaults/default_common_options.py
pubq/defaults/default_connection_events.py
pubq/defaults/default_private_options.py
pubq/http.py
pubq/message.py
pubq/pubq.py
pubq/real_time.py
pubq/real_time_channels.py
pubq/rest.py
pubq/rest_channels.py
pubq/types/__init__.py
pubq/types/channel.py
pubq/types/common_options.py
pubq/types/connection.py
pubq/types/error_info.py
pubq/types/events.py
pubq/types/listeners.py
pubq/types/message.py
pubq/types/private_options.py
pubq/types/states.py
pubq/types/token_options.py
pubq/utils/jwt.py
pubq/utils/storage.py
pubq/utils/time.py
pubq/websocket.py
pubq-1.2.1.dist-info/LICENSE
pubq-1.2.1.dist-info/METADATA
pubq-1.2.1.dist-info/WHEEL
pubq-1.2.1.dist-info/RECORD
