Metadata-Version: 2.1
Name: pubq
Version: 1.2.1
Summary: PUBQ Python SDK
Home-page: https://pubq.io
License: MIT
Author: PUBQ Team
Author-email: dev@pubq.io
Maintainer: PUBQ Team
Maintainer-email: dev@pubq.io
Requires-Python: >=3.8,<4.0
Classifier: Development Status :: 6 - Mature
Classifier: Intended Audience :: Developers
Classifier: License :: OSI Approved :: MIT License
Classifier: Operating System :: OS Independent
Classifier: Programming Language :: Python :: 3
Classifier: Programming Language :: Python :: 3.8
Classifier: Programming Language :: Python :: 3.9
Classifier: Programming Language :: Python :: 3.10
Classifier: Programming Language :: Python :: 3.11
Classifier: Programming Language :: Python :: 3.12
Classifier: Programming Language :: Python :: 3 :: Only
Classifier: Topic :: Software Development :: Libraries :: Python Modules
Requires-Dist: pyee (>=11.0.0,<12.0.0)
Requires-Dist: pyjwt (>=2.8.0,<3.0.0)
Requires-Dist: requests (>=2.31.0,<3.0.0)
Requires-Dist: socketclusterclient (>=1.3.6,<2.0.0)
Project-URL: Documentation, https://github.com/pubqio/pubq-python
Project-URL: Repository, https://github.com/pubqio/pubq-python
